LICENSE
MANIFEST.in
README.txt
setup.cfg
setup.py
TracGoogleAds.egg-info/PKG-INFO
TracGoogleAds.egg-info/SOURCES.txt
TracGoogleAds.egg-info/dependency_links.txt
TracGoogleAds.egg-info/entry_points.txt
TracGoogleAds.egg-info/namespace_packages.txt
TracGoogleAds.egg-info/requires.txt
TracGoogleAds.egg-info/top_level.txt
tracext/__init__.py
tracext/google/__init__.py
tracext/google/ads/__init__.py
tracext/google/ads/admin.py
tracext/google/ads/web_ui.py
tracext/google/ads/htdocs/googleads.css
tracext/google/ads/templates/google_ads_admin.html
tracext/google/ads/templates/google_ads_table.html