Metadata-Version: 1.0
Name: TracGoogleAds
Version: 0.2.2
Summary: Trac plugin designed to display ads on your Trac environment
Home-page: http://google.ufsoft.org
Author: Pedro Algarvio
Author-email: ufs@ufsoft.org
License: BSD
Download-URL: http://python.org/pypi/tracext.google.ads
Keywords: trac plugin google ads
Platform: UNKNOWN
Classifier: Framework :: Trac
